asset_management/__init__.py
asset_management/asset_management.py
asset_management-0.1.0.dist-info/LICENSE
asset_management-0.1.0.dist-info/METADATA
asset_management-0.1.0.dist-info/WHEEL
asset_management-0.1.0.dist-info/top_level.txt
asset_management-0.1.0.dist-info/RECORD
